Metadata-Version: 2.1
Name: rgbprint
Version: 4.0.1
Summary: Print colors and gradients in your terminal. Official github: https://github.com/ddjerqq/rgbprint
Home-page: https://github.com/ddjerqq/rgbprint
Author: ddjerqq
Author-email: ddjerqq@gmail.com
License: GNU
Keywords: rgb print gradient color colorama
Platform: UNKNOWN
License-File: LICENSE
